bdss_client-1.0.1b4.data/data/client/defaults.cfg
bdss_client-1.0.1b4.dist-info/DESCRIPTION.rst
bdss_client-1.0.1b4.dist-info/METADATA
bdss_client-1.0.1b4.dist-info/RECORD
bdss_client-1.0.1b4.dist-info/WHEEL
bdss_client-1.0.1b4.dist-info/entry_points.txt
bdss_client-1.0.1b4.dist-info/metadata.json
bdss_client-1.0.1b4.dist-info/top_level.txt
client/__init__.py
client/__main__.py
client/config.py
client/defaults.cfg
client/util.py
client/version.py
client/actions/__init__.py
client/actions/check_configuration_action.py
client/actions/config_action.py
client/actions/mechanisms_action.py
client/actions/sources_action.py
client/actions/test_files_action.py
client/actions/transfer_action.py
client/actions/version_action.py
client/transfer/__init__.py
client/transfer/base.py
client/transfer/data.py
client/transfer/reporting.py
client/transfer/mechanisms/__init__.py
client/transfer/mechanisms/anonymous_gridftp.py
client/transfer/mechanisms/aspera.py
client/transfer/mechanisms/base.py
client/transfer/mechanisms/curl.py
client/transfer/mechanisms/gridftp_lite.py
client/transfer/mechanisms/scp.py
client/transfer/mechanisms/session_authenticated_curl.py
client/transfer/verification/__init__.py
client/transfer/verification/md5_checksum_verification.py
client/transfer/verification/sra_toolkit_vdb_validate_verification.py
tests/__init__.py
tests/test_util.py
tests/actions/__init__.py
tests/actions/test_sources_action.py
tests/actions/test_test_files_action.py
tests/actions/test_transfer_action.py
tests/transfer/__init__.py
tests/transfer/test_transfer.py
tests/transfer/mechanisms/__init__.py
tests/transfer/mechanisms/test_default_mechanism.py
tests/transfer/mechanisms/test_user_options.py
tests/transfer/verification/__init__.py
tests/transfer/verification/test_md5_checksum.py
tests/transfer/verification/test_sra_toolkit_vdb_validate_verification.py
