Metadata-Version: 2.0
Name: bdss-client
Version: 1.0.1b4
Summary: Big Data Smart Socket client
Home-page: https://github.com/feltus/BDSS
Author: Nick Watts
Author-email: nick@nawatts.com
License: GPLv2
Platform: UNKNOWN
Classifier: Development Status :: 4 - Beta
Classifier: Environment :: Console
Classifier: Intended Audience :: Science/Research
Classifier: License :: OSI Approved :: GNU General Public License v2 (GPLv2)
Classifier: Natural Language :: English
Classifier: Programming Language :: Python :: 3.4
Classifier: Programming Language :: Python :: 3.5
Classifier: Topic :: Scientific/Engineering
Requires-Dist: colorlog (==2.7.0)
Requires-Dist: requests (==2.8.1)
Requires-Dist: six (==1.10.0)
Requires-Dist: voluptuous (==0.8.11)
